setup.py
pydedustapi/__init__.py
pydedustapi/async_dedust.py
pydedustapi/dedust.py
pydedustapi/tokens.py
pydedustapi.egg-info/PKG-INFO
pydedustapi.egg-info/SOURCES.txt
pydedustapi.egg-info/dependency_links.txt
pydedustapi.egg-info/requires.txt
pydedustapi.egg-info/top_level.txt