Metadata-Version: 2.1
Name: pydedustapi
Version: 0.2.1
Summary: A Python library for interacting with the DeDust API
Home-page: https://github.com/labfunny/py-dedust-api
Author: Max
License: MIT
Classifier: Programming Language :: Python :: 3.6
Requires-Dist: requests
Requires-Dist: asyncio
Requires-Dist: aiohttp
